[{"model": "user.users", "pk": 1, "fields": {"password": "pbkdf2_sha256$720000$YzFFpivIgOVu9C6bfMV5JH$um3uUYBqJfMmCxglywmfT6rOFVvGq4c/TOJgE5UX9RE=", "last_login": null, "email": "prajwalmalla16@gmail.com", "username": "", "firstname": null, "lastname": null, "dob": null, "bio": null, "gender": 0, "country": null, "img_cover": "", "img_profile": "", "theme": null, "is_artist": false, "is_staff": true, "is_superuser": true, "is_active": true, "is_deleted": false, "is_disabled": false, "created_by": null, "created_at": "2024-06-06T06:48:10.042Z", "modified_by": null, "groups": [], "user_permissions": []}}, {"model": "user.users", "pk": 2, "fields": {"password": "pbkdf2_sha256$720000$y99PdNGkClMVGBNGcpBm6p$qUhK6UZF7+8rUNEt5KECUSEjr8Yhqp/fxYh3mkwcR4M=", "last_login": null, "email": "Shallumlama@gmail.com", "username": "Shallum", "firstname": "Shallum", "lastname": "Lama", "dob": "2001-06-06", "bio": null, "gender": 0, "country": "Nepal", "img_cover": "uploads/user/afro-guitar-colorful-music-sunglasses-digital-art-hd-wallpaper-uhdpaper.com-2221n.jpg", "img_profile": "uploads/user/486x486bb.png", "theme": 2, "is_artist": true, "is_staff": false, "is_superuser": false, "is_active": true, "is_deleted": false, "is_disabled": false, "created_by": null, "created_at": "2024-06-06T06:50:51.123Z", "modified_by": null, "groups": [], "user_permissions": []}}, {"model": "user.users", "pk": 3, "fields": {"password": "pbkdf2_sha256$720000$L26GmdvKArU706OOe9OB5o$Ete3CDXr9jRT/OgCMD64WCzhEL9kSLhfFnwhjHi9Ic8=", "last_login": null, "email": "Olivia@gmail.com", "username": "Olivia", "firstname": "Olivia", "lastname": "Rodrigo", "dob": "2003-02-20", "bio": null, "gender": 1, "country": "USA", "img_cover": "uploads/user/0753d43660c8062c4b9e397da4c9d969.jpg", "img_profile": "uploads/user/8bcbd67e74c87d598880d0a4dd511248.jpg", "theme": 19, "is_artist": true, "is_staff": false, "is_superuser": false, "is_active": true, "is_deleted": false, "is_disabled": false, "created_by": null, "created_at": "2024-06-06T09:45:21.754Z", "modified_by": null, "groups": [], "user_permissions": []}}, {"model": "user.users", "pk": 4, "fields": {"password": "pbkdf2_sha256$720000$qOIWxKQHIG1WRzsXFwnjP5$tMAIme89aeoP8I7/+FYxr8ybmTY6QwA9ebDQ/eAXQjM=", "last_login": null, "email": "Nirmalvia@gmail.com", "username": "Nirmalvia", "firstname": "Nirmalsa", "lastname": "Malla", "dob": "2024-06-13", "bio": null, "gender": 0, "country": "Armenia", "img_cover": "uploads/default/cover.jpeg", "img_profile": "uploads/default/defaultUser.jpg", "theme": null, "is_artist": true, "is_staff": false, "is_superuser": false, "is_active": true, "is_deleted": false, "is_disabled": false, "created_by": null, "created_at": "2024-06-12T04:41:04.428Z", "modified_by": null, "groups": [], "user_permissions": []}}, {"model": "user.users", "pk": 5, "fields": {"password": "pbkdf2_sha256$720000$3IQe1bhkH4y4wBMuiDz5HL$qqQrI+sMa4/Y06nvHSID0ZmRhfeslnWrw6FeWXQf6lg=", "last_login": null, "email": "raichu@gmail.com", "username": "raichu", "firstname": "Raichu", "lastname": "Malla", "dob": "2001-04-25", "bio": null, "gender": 1, "country": "Nepal", "img_cover": "uploads/default/cover.jpeg", "img_profile": "uploads/user/profile/9c8b1d12f5ecfc6da24d8d5f97acce44.jpg", "theme": null, "is_artist": false, "is_staff": false, "is_superuser": false, "is_active": true, "is_deleted": false, "is_disabled": false, "created_by": null, "created_at": "2024-06-12T07:04:24.372Z", "modified_by": null, "groups": [], "user_permissions": []}}, {"model": "user.users", "pk": 6, "fields": {"password": "pbkdf2_sha256$720000$iBq8LP5WiNoMaZQFiA3p2d$BqiosRG58du8KOwDIlXg7SUbQyessZSbSCLPwHE23bk=", "last_login": null, "email": "eminem@gmail.com", "username": "Eminem", "firstname": "Marshall", "lastname": "Bruce", "dob": "1972-10-17", "bio": null, "gender": 0, "country": "South Korea", "img_cover": "uploads/user/cover/wallpaperflare.com_wallpaper.jpg", "img_profile": "uploads/user/profile/d0e56ad7c58cc67a3474324c6bce3c59.jpg", "theme": 10, "is_artist": true, "is_staff": false, "is_superuser": false, "is_active": true, "is_deleted": false, "is_disabled": false, "created_by": null, "created_at": "2024-06-12T07:08:37.635Z", "modified_by": null, "groups": [], "user_permissions": []}}]